blend2d/__init__.py
blend2d/blend2d_ext.cpython-313t-darwin.so
blend2d/blend2d_ext.pyi
blend2d/py.typed
blend2d_py-2025.5.0.dist-info/METADATA
blend2d_py-2025.5.0.dist-info/WHEEL
blend2d_py-2025.5.0.dist-info/licenses/LICENSE
blend2d_py-2025.5.0.dist-info/RECORD
