Metadata-Version: 2.4
Name: blend2d-py
Version: 2025.5.0
Summary: Python bindings for Blend2D (via nanobind)
Author-Email: "Shiguredo Inc." <contact+pypi@shiguredo.jp>
License-Expression: Apache-2.0
License-File: LICENSE
Classifier: Programming Language :: C++
Classifier: Programming Language :: Python :: 3
Classifier: Programming Language :: Python :: 3 :: Only
Classifier: Programming Language :: Python :: 3.12
Classifier: Programming Language :: Python :: 3.13
Classifier: Programming Language :: Python :: 3.14
Classifier: Programming Language :: Python :: Free Threading :: 2 - Beta
Classifier: Operating System :: MacOS :: MacOS X
Classifier: Operating System :: POSIX :: Linux
Classifier: Operating System :: Microsoft :: Windows
Project-URL: Source, https://github.com/shiguredo/blend2d-py
Project-URL: Discord, https://discord.gg/shiguredo
Requires-Python: >=3.12
